ndtools/__init__.py
ndtools/fun_binary_graph.py
ndtools/graphs.py
ndtools/io.py
ndtools/network_generator.py
ndtools/staged_max_flow.py
ndtools_duco-0.1.8.dist-info/licenses/LICENSE
ndtools_duco-0.1.8.dist-info/METADATA
ndtools_duco-0.1.8.dist-info/WHEEL
ndtools_duco-0.1.8.dist-info/top_level.txt
ndtools_duco-0.1.8.dist-info/RECORD
