Metadata-Version: 2.4
Name: ndtools-duco
Version: 0.1.8
License-Expression: MIT
Requires-Python: >=3.9
License-File: LICENSE
Requires-Dist: networkx>=3.0
Requires-Dist: pyyaml>=6.0
Requires-Dist: jsonschema>=4.0
Requires-Dist: matplotlib>=3.4
Requires-Dist: scipy>=1.9
Dynamic: license-file
